gcp_jwt-0.1.9.data/data/resources/requirements.txt
gcp_jwt-0.1.9.data/data/resources/setup.json
gcpjwt/__init__.py
gcpjwt/jwt.py
gcpjwt/jwt_signer.py
gcp_jwt-0.1.9.dist-info/LICENSE
gcp_jwt-0.1.9.dist-info/METADATA
gcp_jwt-0.1.9.dist-info/WHEEL
gcp_jwt-0.1.9.dist-info/top_level.txt
gcp_jwt-0.1.9.dist-info/RECORD
