Metadata-Version: 2.1
Name: gcp-jwt
Version: 0.1.9
Summary: Generate, Sign and verify JWTs using GCP KMS.
Home-page: https://github.com/BinarSkugga/gcp-jwt
Author: Charles Smith
License: GNU GPLv3
Platform: UNKNOWN
Requires-Python: >=3.6
Requires-Dist: cryptography
Requires-Dist: google-cloud-kms
